<annotation>
	<folder></folder>
	<filename>IMG_2950_jpg.rf.39e44d131f9fe339630064543c6cb260.jpg</filename>
	<path>IMG_2950_jpg.rf.39e44d131f9fe339630064543c6cb260.jpg</path>
	<source>
		<database>roboflow.ai</database>
	</source>
	<size>
		<width>1024</width>
		<height>1024</height>
		<depth>3</depth>
	</size>
	<segmented>0</segmented>
	<object>
		<name>rice</name>
		<pose>Unspecified</pose>
		<truncated>0</truncated>
		<difficult>0</difficult>
		<occluded>0</occluded>
		<bndbox>
			<xmin>787</xmin>
			<xmax>844</xmax>
			<ymin>771</ymin>
			<ymax>837</ymax>
		</bndbox>
	</object>
	<object>
		<name>rice</name>
		<pose>Unspecified</pose>
		<truncated>0</truncated>
		<difficult>0</difficult>
		<occluded>0</occluded>
		<bndbox>
			<xmin>729</xmin>
			<xmax>803</xmax>
			<ymin>787</ymin>
			<ymax>846</ymax>
		</bndbox>
	</object>
	<object>
		<name>rice</name>
		<pose>Unspecified</pose>
		<truncated>0</truncated>
		<difficult>0</difficult>
		<occluded>0</occluded>
		<bndbox>
			<xmin>700</xmin>
			<xmax>780</xmax>
			<ymin>842</ymin>
			<ymax>902</ymax>
		</bndbox>
	</object>
	<object>
		<name>rice</name>
		<pose>Unspecified</pose>
		<truncated>0</truncated>
		<difficult>0</difficult>
		<occluded>0</occluded>
		<bndbox>
			<xmin>607</xmin>
			<xmax>690</xmax>
			<ymin>820</ymin>
			<ymax>874</ymax>
		</bndbox>
	</object>
	<object>
		<name>rice</name>
		<pose>Unspecified</pose>
		<truncated>0</truncated>
		<difficult>0</difficult>
		<occluded>0</occluded>
		<bndbox>
			<xmin>365</xmin>
			<xmax>422</xmax>
			<ymin>899</ymin>
			<ymax>966</ymax>
		</bndbox>
	</object>
	<object>
		<name>rice</name>
		<pose>Unspecified</pose>
		<truncated>0</truncated>
		<difficult>0</difficult>
		<occluded>0</occluded>
		<bndbox>
			<xmin>393</xmin>
			<xmax>449</xmax>
			<ymin>908</ymin>
			<ymax>976</ymax>
		</bndbox>
	</object>
	<object>
		<name>rice</name>
		<pose>Unspecified</pose>
		<truncated>0</truncated>
		<difficult>0</difficult>
		<occluded>0</occluded>
		<bndbox>
			<xmin>424</xmin>
			<xmax>489</xmax>
			<ymin>870</ymin>
			<ymax>947</ymax>
		</bndbox>
	</object>
	<object>
		<name>rice</name>
		<pose>Unspecified</pose>
		<truncated>0</truncated>
		<difficult>0</difficult>
		<occluded>0</occluded>
		<bndbox>
			<xmin>447</xmin>
			<xmax>491</xmax>
			<ymin>840</ymin>
			<ymax>908</ymax>
		</bndbox>
	</object>
	<object>
		<name>rice</name>
		<pose>Unspecified</pose>
		<truncated>0</truncated>
		<difficult>0</difficult>
		<occluded>0</occluded>
		<bndbox>
			<xmin>476</xmin>
			<xmax>521</xmax>
			<ymin>844</ymin>
			<ymax>912</ymax>
		</bndbox>
	</object>
	<object>
		<name>rice</name>
		<pose>Unspecified</pose>
		<truncated>0</truncated>
		<difficult>0</difficult>
		<occluded>0</occluded>
		<bndbox>
			<xmin>510</xmin>
			<xmax>555</xmax>
			<ymin>848</ymin>
			<ymax>906</ymax>
		</bndbox>
	</object>
	<object>
		<name>rice</name>
		<pose>Unspecified</pose>
		<truncated>0</truncated>
		<difficult>0</difficult>
		<occluded>0</occluded>
		<bndbox>
			<xmin>468</xmin>
			<xmax>533</xmax>
			<ymin>805</ymin>
			<ymax>871</ymax>
		</bndbox>
	</object>
	<object>
		<name>rice</name>
		<pose>Unspecified</pose>
		<truncated>0</truncated>
		<difficult>0</difficult>
		<occluded>0</occluded>
		<bndbox>
			<xmin>497</xmin>
			<xmax>558</xmax>
			<ymin>769</ymin>
			<ymax>853</ymax>
		</bndbox>
	</object>
	<object>
		<name>rice</name>
		<pose>Unspecified</pose>
		<truncated>0</truncated>
		<difficult>0</difficult>
		<occluded>0</occluded>
		<bndbox>
			<xmin>523</xmin>
			<xmax>580</xmax>
			<ymin>781</ymin>
			<ymax>851</ymax>
		</bndbox>
	</object>
	<object>
		<name>rice</name>
		<pose>Unspecified</pose>
		<truncated>0</truncated>
		<difficult>0</difficult>
		<occluded>0</occluded>
		<bndbox>
			<xmin>543</xmin>
			<xmax>620</xmax>
			<ymin>788</ymin>
			<ymax>862</ymax>
		</bndbox>
	</object>
	<object>
		<name>rice</name>
		<pose>Unspecified</pose>
		<truncated>0</truncated>
		<difficult>0</difficult>
		<occluded>0</occluded>
		<bndbox>
			<xmin>596</xmin>
			<xmax>675</xmax>
			<ymin>767</ymin>
			<ymax>821</ymax>
		</bndbox>
	</object>
	<object>
		<name>rice</name>
		<pose>Unspecified</pose>
		<truncated>0</truncated>
		<difficult>0</difficult>
		<occluded>0</occluded>
		<bndbox>
			<xmin>711</xmin>
			<xmax>777</xmax>
			<ymin>731</ymin>
			<ymax>801</ymax>
		</bndbox>
	</object>
	<object>
		<name>rice</name>
		<pose>Unspecified</pose>
		<truncated>0</truncated>
		<difficult>0</difficult>
		<occluded>0</occluded>
		<bndbox>
			<xmin>743</xmin>
			<xmax>799</xmax>
			<ymin>687</ymin>
			<ymax>760</ymax>
		</bndbox>
	</object>
	<object>
		<name>rice</name>
		<pose>Unspecified</pose>
		<truncated>0</truncated>
		<difficult>0</difficult>
		<occluded>0</occluded>
		<bndbox>
			<xmin>774</xmin>
			<xmax>843</xmax>
			<ymin>672</ymin>
			<ymax>724</ymax>
		</bndbox>
	</object>
	<object>
		<name>rice</name>
		<pose>Unspecified</pose>
		<truncated>0</truncated>
		<difficult>0</difficult>
		<occluded>0</occluded>
		<bndbox>
			<xmin>747</xmin>
			<xmax>825</xmax>
			<ymin>650</ymin>
			<ymax>699</ymax>
		</bndbox>
	</object>
	<object>
		<name>rice</name>
		<pose>Unspecified</pose>
		<truncated>0</truncated>
		<difficult>0</difficult>
		<occluded>0</occluded>
		<bndbox>
			<xmin>691</xmin>
			<xmax>762</xmax>
			<ymin>709</ymin>
			<ymax>779</ymax>
		</bndbox>
	</object>
	<object>
		<name>rice</name>
		<pose>Unspecified</pose>
		<truncated>0</truncated>
		<difficult>0</difficult>
		<occluded>0</occluded>
		<bndbox>
			<xmin>634</xmin>
			<xmax>711</xmax>
			<ymin>727</ymin>
			<ymax>784</ymax>
		</bndbox>
	</object>
	<object>
		<name>rice</name>
		<pose>Unspecified</pose>
		<truncated>0</truncated>
		<difficult>0</difficult>
		<occluded>0</occluded>
		<bndbox>
			<xmin>562</xmin>
			<xmax>637</xmax>
			<ymin>752</ymin>
			<ymax>801</ymax>
		</bndbox>
	</object>
	<object>
		<name>rice</name>
		<pose>Unspecified</pose>
		<truncated>0</truncated>
		<difficult>0</difficult>
		<occluded>0</occluded>
		<bndbox>
			<xmin>442</xmin>
			<xmax>522</xmax>
			<ymin>734</ymin>
			<ymax>799</ymax>
		</bndbox>
	</object>
	<object>
		<name>rice</name>
		<pose>Unspecified</pose>
		<truncated>0</truncated>
		<difficult>0</difficult>
		<occluded>0</occluded>
		<bndbox>
			<xmin>540</xmin>
			<xmax>617</xmax>
			<ymin>733</ymin>
			<ymax>780</ymax>
		</bndbox>
	</object>
	<object>
		<name>rice</name>
		<pose>Unspecified</pose>
		<truncated>0</truncated>
		<difficult>0</difficult>
		<occluded>0</occluded>
		<bndbox>
			<xmin>515</xmin>
			<xmax>579</xmax>
			<ymin>700</ymin>
			<ymax>770</ymax>
		</bndbox>
	</object>
	<object>
		<name>rice</name>
		<pose>Unspecified</pose>
		<truncated>0</truncated>
		<difficult>0</difficult>
		<occluded>0</occluded>
		<bndbox>
			<xmin>551</xmin>
			<xmax>620</xmax>
			<ymin>705</ymin>
			<ymax>752</ymax>
		</bndbox>
	</object>
	<object>
		<name>rice</name>
		<pose>Unspecified</pose>
		<truncated>0</truncated>
		<difficult>0</difficult>
		<occluded>0</occluded>
		<bndbox>
			<xmin>737</xmin>
			<xmax>814</xmax>
			<ymin>604</ymin>
			<ymax>670</ymax>
		</bndbox>
	</object>
	<object>
		<name>rice</name>
		<pose>Unspecified</pose>
		<truncated>0</truncated>
		<difficult>0</difficult>
		<occluded>0</occluded>
		<bndbox>
			<xmin>684</xmin>
			<xmax>758</xmax>
			<ymin>677</ymin>
			<ymax>726</ymax>
		</bndbox>
	</object>
	<object>
		<name>rice</name>
		<pose>Unspecified</pose>
		<truncated>0</truncated>
		<difficult>0</difficult>
		<occluded>0</occluded>
		<bndbox>
			<xmin>645</xmin>
			<xmax>718</xmax>
			<ymin>704</ymin>
			<ymax>754</ymax>
		</bndbox>
	</object>
	<object>
		<name>rice</name>
		<pose>Unspecified</pose>
		<truncated>0</truncated>
		<difficult>0</difficult>
		<occluded>0</occluded>
		<bndbox>
			<xmin>604</xmin>
			<xmax>676</xmax>
			<ymin>691</ymin>
			<ymax>756</ymax>
		</bndbox>
	</object>
	<object>
		<name>rice</name>
		<pose>Unspecified</pose>
		<truncated>0</truncated>
		<difficult>0</difficult>
		<occluded>0</occluded>
		<bndbox>
			<xmin>696</xmin>
			<xmax>754</xmax>
			<ymin>633</ymin>
			<ymax>692</ymax>
		</bndbox>
	</object>
	<object>
		<name>rice</name>
		<pose>Unspecified</pose>
		<truncated>0</truncated>
		<difficult>0</difficult>
		<occluded>0</occluded>
		<bndbox>
			<xmin>655</xmin>
			<xmax>710</xmax>
			<ymin>604</ymin>
			<ymax>680</ymax>
		</bndbox>
	</object>
	<object>
		<name>rice</name>
		<pose>Unspecified</pose>
		<truncated>0</truncated>
		<difficult>0</difficult>
		<occluded>0</occluded>
		<bndbox>
			<xmin>656</xmin>
			<xmax>725</xmax>
			<ymin>664</ymin>
			<ymax>719</ymax>
		</bndbox>
	</object>
	<object>
		<name>rice</name>
		<pose>Unspecified</pose>
		<truncated>0</truncated>
		<difficult>0</difficult>
		<occluded>0</occluded>
		<bndbox>
			<xmin>601</xmin>
			<xmax>644</xmax>
			<ymin>665</ymin>
			<ymax>735</ymax>
		</bndbox>
	</object>
	<object>
		<name>rice</name>
		<pose>Unspecified</pose>
		<truncated>0</truncated>
		<difficult>0</difficult>
		<occluded>0</occluded>
		<bndbox>
			<xmin>576</xmin>
			<xmax>625</xmax>
			<ymin>658</ymin>
			<ymax>713</ymax>
		</bndbox>
	</object>
	<object>
		<name>rice</name>
		<pose>Unspecified</pose>
		<truncated>0</truncated>
		<difficult>0</difficult>
		<occluded>0</occluded>
		<bndbox>
			<xmin>443</xmin>
			<xmax>513</xmax>
			<ymin>690</ymin>
			<ymax>745</ymax>
		</bndbox>
	</object>
	<object>
		<name>rice</name>
		<pose>Unspecified</pose>
		<truncated>0</truncated>
		<difficult>0</difficult>
		<occluded>0</occluded>
		<bndbox>
			<xmin>496</xmin>
			<xmax>546</xmax>
			<ymin>662</ymin>
			<ymax>738</ymax>
		</bndbox>
	</object>
	<object>
		<name>rice</name>
		<pose>Unspecified</pose>
		<truncated>0</truncated>
		<difficult>0</difficult>
		<occluded>0</occluded>
		<bndbox>
			<xmin>530</xmin>
			<xmax>596</xmax>
			<ymin>659</ymin>
			<ymax>728</ymax>
		</bndbox>
	</object>
	<object>
		<name>rice</name>
		<pose>Unspecified</pose>
		<truncated>0</truncated>
		<difficult>0</difficult>
		<occluded>0</occluded>
		<bndbox>
			<xmin>629</xmin>
			<xmax>685</xmax>
			<ymin>612</ymin>
			<ymax>695</ymax>
		</bndbox>
	</object>
	<object>
		<name>rice</name>
		<pose>Unspecified</pose>
		<truncated>0</truncated>
		<difficult>0</difficult>
		<occluded>0</occluded>
		<bndbox>
			<xmin>616</xmin>
			<xmax>669</xmax>
			<ymin>633</ymin>
			<ymax>706</ymax>
		</bndbox>
	</object>
	<object>
		<name>rice</name>
		<pose>Unspecified</pose>
		<truncated>0</truncated>
		<difficult>0</difficult>
		<occluded>0</occluded>
		<bndbox>
			<xmin>703</xmin>
			<xmax>787</xmax>
			<ymin>569</ymin>
			<ymax>632</ymax>
		</bndbox>
	</object>
	<object>
		<name>rice</name>
		<pose>Unspecified</pose>
		<truncated>0</truncated>
		<difficult>0</difficult>
		<occluded>0</occluded>
		<bndbox>
			<xmin>649</xmin>
			<xmax>729</xmax>
			<ymin>558</ymin>
			<ymax>610</ymax>
		</bndbox>
	</object>
	<object>
		<name>rice</name>
		<pose>Unspecified</pose>
		<truncated>0</truncated>
		<difficult>0</difficult>
		<occluded>0</occluded>
		<bndbox>
			<xmin>737</xmin>
			<xmax>793</xmax>
			<ymin>489</ymin>
			<ymax>572</ymax>
		</bndbox>
	</object>
	<object>
		<name>rice</name>
		<pose>Unspecified</pose>
		<truncated>0</truncated>
		<difficult>0</difficult>
		<occluded>0</occluded>
		<bndbox>
			<xmin>684</xmin>
			<xmax>763</xmax>
			<ymin>525</ymin>
			<ymax>593</ymax>
		</bndbox>
	</object>
	<object>
		<name>rice</name>
		<pose>Unspecified</pose>
		<truncated>0</truncated>
		<difficult>0</difficult>
		<occluded>0</occluded>
		<bndbox>
			<xmin>647</xmin>
			<xmax>724</xmax>
			<ymin>501</ymin>
			<ymax>554</ymax>
		</bndbox>
	</object>
	<object>
		<name>rice</name>
		<pose>Unspecified</pose>
		<truncated>0</truncated>
		<difficult>0</difficult>
		<occluded>0</occluded>
		<bndbox>
			<xmin>279</xmin>
			<xmax>330</xmax>
			<ymin>638</ymin>
			<ymax>705</ymax>
		</bndbox>
	</object>
	<object>
		<name>rice</name>
		<pose>Unspecified</pose>
		<truncated>0</truncated>
		<difficult>0</difficult>
		<occluded>0</occluded>
		<bndbox>
			<xmin>305</xmin>
			<xmax>370</xmax>
			<ymin>629</ymin>
			<ymax>696</ymax>
		</bndbox>
	</object>
	<object>
		<name>rice</name>
		<pose>Unspecified</pose>
		<truncated>0</truncated>
		<difficult>0</difficult>
		<occluded>0</occluded>
		<bndbox>
			<xmin>331</xmin>
			<xmax>402</xmax>
			<ymin>629</ymin>
			<ymax>697</ymax>
		</bndbox>
	</object>
	<object>
		<name>rice</name>
		<pose>Unspecified</pose>
		<truncated>0</truncated>
		<difficult>0</difficult>
		<occluded>0</occluded>
		<bndbox>
			<xmin>418</xmin>
			<xmax>488</xmax>
			<ymin>618</ymin>
			<ymax>673</ymax>
		</bndbox>
	</object>
	<object>
		<name>rice</name>
		<pose>Unspecified</pose>
		<truncated>0</truncated>
		<difficult>0</difficult>
		<occluded>0</occluded>
		<bndbox>
			<xmin>490</xmin>
			<xmax>563</xmax>
			<ymin>623</ymin>
			<ymax>687</ymax>
		</bndbox>
	</object>
	<object>
		<name>rice</name>
		<pose>Unspecified</pose>
		<truncated>0</truncated>
		<difficult>0</difficult>
		<occluded>0</occluded>
		<bndbox>
			<xmin>553</xmin>
			<xmax>631</xmax>
			<ymin>624</ymin>
			<ymax>681</ymax>
		</bndbox>
	</object>
	<object>
		<name>rice</name>
		<pose>Unspecified</pose>
		<truncated>0</truncated>
		<difficult>0</difficult>
		<occluded>0</occluded>
		<bndbox>
			<xmin>511</xmin>
			<xmax>586</xmax>
			<ymin>602</ymin>
			<ymax>662</ymax>
		</bndbox>
	</object>
	<object>
		<name>rice</name>
		<pose>Unspecified</pose>
		<truncated>0</truncated>
		<difficult>0</difficult>
		<occluded>0</occluded>
		<bndbox>
			<xmin>517</xmin>
			<xmax>595</xmax>
			<ymin>582</ymin>
			<ymax>639</ymax>
		</bndbox>
	</object>
	<object>
		<name>rice</name>
		<pose>Unspecified</pose>
		<truncated>0</truncated>
		<difficult>0</difficult>
		<occluded>0</occluded>
		<bndbox>
			<xmin>435</xmin>
			<xmax>514</xmax>
			<ymin>590</ymin>
			<ymax>656</ymax>
		</bndbox>
	</object>
	<object>
		<name>rice</name>
		<pose>Unspecified</pose>
		<truncated>0</truncated>
		<difficult>0</difficult>
		<occluded>0</occluded>
		<bndbox>
			<xmin>314</xmin>
			<xmax>400</xmax>
			<ymin>585</ymin>
			<ymax>640</ymax>
		</bndbox>
	</object>
	<object>
		<name>rice</name>
		<pose>Unspecified</pose>
		<truncated>0</truncated>
		<difficult>0</difficult>
		<occluded>0</occluded>
		<bndbox>
			<xmin>381</xmin>
			<xmax>455</xmax>
			<ymin>577</ymin>
			<ymax>633</ymax>
		</bndbox>
	</object>
	<object>
		<name>rice</name>
		<pose>Unspecified</pose>
		<truncated>0</truncated>
		<difficult>0</difficult>
		<occluded>0</occluded>
		<bndbox>
			<xmin>587</xmin>
			<xmax>660</xmax>
			<ymin>508</ymin>
			<ymax>587</ymax>
		</bndbox>
	</object>
	<object>
		<name>rice</name>
		<pose>Unspecified</pose>
		<truncated>0</truncated>
		<difficult>0</difficult>
		<occluded>0</occluded>
		<bndbox>
			<xmin>534</xmin>
			<xmax>608</xmax>
			<ymin>557</ymin>
			<ymax>607</ymax>
		</bndbox>
	</object>
	<object>
		<name>rice</name>
		<pose>Unspecified</pose>
		<truncated>0</truncated>
		<difficult>0</difficult>
		<occluded>0</occluded>
		<bndbox>
			<xmin>550</xmin>
			<xmax>625</xmax>
			<ymin>519</ymin>
			<ymax>573</ymax>
		</bndbox>
	</object>
	<object>
		<name>rice</name>
		<pose>Unspecified</pose>
		<truncated>0</truncated>
		<difficult>0</difficult>
		<occluded>0</occluded>
		<bndbox>
			<xmin>642</xmin>
			<xmax>710</xmax>
			<ymin>465</ymin>
			<ymax>523</ymax>
		</bndbox>
	</object>
	<object>
		<name>rice</name>
		<pose>Unspecified</pose>
		<truncated>0</truncated>
		<difficult>0</difficult>
		<occluded>0</occluded>
		<bndbox>
			<xmin>690</xmin>
			<xmax>764</xmax>
			<ymin>422</ymin>
			<ymax>477</ymax>
		</bndbox>
	</object>
	<object>
		<name>rice</name>
		<pose>Unspecified</pose>
		<truncated>0</truncated>
		<difficult>0</difficult>
		<occluded>0</occluded>
		<bndbox>
			<xmin>636</xmin>
			<xmax>706</xmax>
			<ymin>431</ymin>
			<ymax>480</ymax>
		</bndbox>
	</object>
	<object>
		<name>rice</name>
		<pose>Unspecified</pose>
		<truncated>0</truncated>
		<difficult>0</difficult>
		<occluded>0</occluded>
		<bndbox>
			<xmin>607</xmin>
			<xmax>671</xmax>
			<ymin>351</ymin>
			<ymax>416</ymax>
		</bndbox>
	</object>
	<object>
		<name>rice</name>
		<pose>Unspecified</pose>
		<truncated>0</truncated>
		<difficult>0</difficult>
		<occluded>0</occluded>
		<bndbox>
			<xmin>643</xmin>
			<xmax>716</xmax>
			<ymin>378</ymin>
			<ymax>440</ymax>
		</bndbox>
	</object>
	<object>
		<name>rice</name>
		<pose>Unspecified</pose>
		<truncated>0</truncated>
		<difficult>0</difficult>
		<occluded>0</occluded>
		<bndbox>
			<xmin>664</xmin>
			<xmax>735</xmax>
			<ymin>339</ymin>
			<ymax>414</ymax>
		</bndbox>
	</object>
	<object>
		<name>rice</name>
		<pose>Unspecified</pose>
		<truncated>0</truncated>
		<difficult>0</difficult>
		<occluded>0</occluded>
		<bndbox>
			<xmin>689</xmin>
			<xmax>756</xmax>
			<ymin>247</ymin>
			<ymax>326</ymax>
		</bndbox>
	</object>
	<object>
		<name>rice</name>
		<pose>Unspecified</pose>
		<truncated>0</truncated>
		<difficult>0</difficult>
		<occluded>0</occluded>
		<bndbox>
			<xmin>658</xmin>
			<xmax>707</xmax>
			<ymin>260</ymin>
			<ymax>333</ymax>
		</bndbox>
	</object>
	<object>
		<name>rice</name>
		<pose>Unspecified</pose>
		<truncated>0</truncated>
		<difficult>0</difficult>
		<occluded>0</occluded>
		<bndbox>
			<xmin>549</xmin>
			<xmax>613</xmax>
			<ymin>271</ymin>
			<ymax>347</ymax>
		</bndbox>
	</object>
	<object>
		<name>rice</name>
		<pose>Unspecified</pose>
		<truncated>0</truncated>
		<difficult>0</difficult>
		<occluded>0</occluded>
		<bndbox>
			<xmin>592</xmin>
			<xmax>655</xmax>
			<ymin>271</ymin>
			<ymax>336</ymax>
		</bndbox>
	</object>
	<object>
		<name>rice</name>
		<pose>Unspecified</pose>
		<truncated>0</truncated>
		<difficult>0</difficult>
		<occluded>0</occluded>
		<bndbox>
			<xmin>609</xmin>
			<xmax>665</xmax>
			<ymin>205</ymin>
			<ymax>284</ymax>
		</bndbox>
	</object>
	<object>
		<name>rice</name>
		<pose>Unspecified</pose>
		<truncated>0</truncated>
		<difficult>0</difficult>
		<occluded>0</occluded>
		<bndbox>
			<xmin>646</xmin>
			<xmax>707</xmax>
			<ymin>211</ymin>
			<ymax>278</ymax>
		</bndbox>
	</object>
	<object>
		<name>rice</name>
		<pose>Unspecified</pose>
		<truncated>0</truncated>
		<difficult>0</difficult>
		<occluded>0</occluded>
		<bndbox>
			<xmin>618</xmin>
			<xmax>687</xmax>
			<ymin>90</ymin>
			<ymax>165</ymax>
		</bndbox>
	</object>
	<object>
		<name>rice</name>
		<pose>Unspecified</pose>
		<truncated>0</truncated>
		<difficult>0</difficult>
		<occluded>0</occluded>
		<bndbox>
			<xmin>575</xmin>
			<xmax>648</xmax>
			<ymin>119</ymin>
			<ymax>174</ymax>
		</bndbox>
	</object>
	<object>
		<name>rice</name>
		<pose>Unspecified</pose>
		<truncated>0</truncated>
		<difficult>0</difficult>
		<occluded>0</occluded>
		<bndbox>
			<xmin>368</xmin>
			<xmax>464</xmax>
			<ymin>56</ymin>
			<ymax>134</ymax>
		</bndbox>
	</object>
	<object>
		<name>rice</name>
		<pose>Unspecified</pose>
		<truncated>0</truncated>
		<difficult>0</difficult>
		<occluded>0</occluded>
		<bndbox>
			<xmin>440</xmin>
			<xmax>516</xmax>
			<ymin>104</ymin>
			<ymax>167</ymax>
		</bndbox>
	</object>
	<object>
		<name>rice</name>
		<pose>Unspecified</pose>
		<truncated>0</truncated>
		<difficult>0</difficult>
		<occluded>0</occluded>
		<bndbox>
			<xmin>482</xmin>
			<xmax>541</xmax>
			<ymin>154</ymin>
			<ymax>233</ymax>
		</bndbox>
	</object>
	<object>
		<name>rice</name>
		<pose>Unspecified</pose>
		<truncated>0</truncated>
		<difficult>0</difficult>
		<occluded>0</occluded>
		<bndbox>
			<xmin>535</xmin>
			<xmax>607</xmax>
			<ymin>192</ymin>
			<ymax>264</ymax>
		</bndbox>
	</object>
	<object>
		<name>rice</name>
		<pose>Unspecified</pose>
		<truncated>0</truncated>
		<difficult>0</difficult>
		<occluded>0</occluded>
		<bndbox>
			<xmin>511</xmin>
			<xmax>576</xmax>
			<ymin>247</ymin>
			<ymax>307</ymax>
		</bndbox>
	</object>
	<object>
		<name>rice</name>
		<pose>Unspecified</pose>
		<truncated>0</truncated>
		<difficult>0</difficult>
		<occluded>0</occluded>
		<bndbox>
			<xmin>471</xmin>
			<xmax>539</xmax>
			<ymin>250</ymin>
			<ymax>306</ymax>
		</bndbox>
	</object>
	<object>
		<name>rice</name>
		<pose>Unspecified</pose>
		<truncated>0</truncated>
		<difficult>0</difficult>
		<occluded>0</occluded>
		<bndbox>
			<xmin>465</xmin>
			<xmax>545</xmax>
			<ymin>209</ymin>
			<ymax>269</ymax>
		</bndbox>
	</object>
	<object>
		<name>rice</name>
		<pose>Unspecified</pose>
		<truncated>0</truncated>
		<difficult>0</difficult>
		<occluded>0</occluded>
		<bndbox>
			<xmin>572</xmin>
			<xmax>651</xmax>
			<ymin>479</ymin>
			<ymax>531</ymax>
		</bndbox>
	</object>
	<object>
		<name>rice</name>
		<pose>Unspecified</pose>
		<truncated>0</truncated>
		<difficult>0</difficult>
		<occluded>0</occluded>
		<bndbox>
			<xmin>576</xmin>
			<xmax>649</xmax>
			<ymin>443</ymin>
			<ymax>498</ymax>
		</bndbox>
	</object>
	<object>
		<name>rice</name>
		<pose>Unspecified</pose>
		<truncated>0</truncated>
		<difficult>0</difficult>
		<occluded>0</occluded>
		<bndbox>
			<xmin>520</xmin>
			<xmax>599</xmax>
			<ymin>406</ymin>
			<ymax>461</ymax>
		</bndbox>
	</object>
	<object>
		<name>rice</name>
		<pose>Unspecified</pose>
		<truncated>0</truncated>
		<difficult>0</difficult>
		<occluded>0</occluded>
		<bndbox>
			<xmin>529</xmin>
			<xmax>613</xmax>
			<ymin>430</ymin>
			<ymax>481</ymax>
		</bndbox>
	</object>
	<object>
		<name>rice</name>
		<pose>Unspecified</pose>
		<truncated>0</truncated>
		<difficult>0</difficult>
		<occluded>0</occluded>
		<bndbox>
			<xmin>523</xmin>
			<xmax>598</xmax>
			<ymin>461</ymin>
			<ymax>515</ymax>
		</bndbox>
	</object>
	<object>
		<name>rice</name>
		<pose>Unspecified</pose>
		<truncated>0</truncated>
		<difficult>0</difficult>
		<occluded>0</occluded>
		<bndbox>
			<xmin>480</xmin>
			<xmax>550</xmax>
			<ymin>471</ymin>
			<ymax>529</ymax>
		</bndbox>
	</object>
	<object>
		<name>rice</name>
		<pose>Unspecified</pose>
		<truncated>0</truncated>
		<difficult>0</difficult>
		<occluded>0</occluded>
		<bndbox>
			<xmin>517</xmin>
			<xmax>563</xmax>
			<ymin>505</ymin>
			<ymax>579</ymax>
		</bndbox>
	</object>
	<object>
		<name>rice</name>
		<pose>Unspecified</pose>
		<truncated>0</truncated>
		<difficult>0</difficult>
		<occluded>0</occluded>
		<bndbox>
			<xmin>463</xmin>
			<xmax>506</xmax>
			<ymin>504</ymin>
			<ymax>566</ymax>
		</bndbox>
	</object>
	<object>
		<name>rice</name>
		<pose>Unspecified</pose>
		<truncated>0</truncated>
		<difficult>0</difficult>
		<occluded>0</occluded>
		<bndbox>
			<xmin>496</xmin>
			<xmax>542</xmax>
			<ymin>521</ymin>
			<ymax>598</ymax>
		</bndbox>
	</object>
	<object>
		<name>rice</name>
		<pose>Unspecified</pose>
		<truncated>0</truncated>
		<difficult>0</difficult>
		<occluded>0</occluded>
		<bndbox>
			<xmin>485</xmin>
			<xmax>531</xmax>
			<ymin>554</ymin>
			<ymax>624</ymax>
		</bndbox>
	</object>
	<object>
		<name>rice</name>
		<pose>Unspecified</pose>
		<truncated>0</truncated>
		<difficult>0</difficult>
		<occluded>0</occluded>
		<bndbox>
			<xmin>448</xmin>
			<xmax>498</xmax>
			<ymin>529</ymin>
			<ymax>610</ymax>
		</bndbox>
	</object>
	<object>
		<name>rice</name>
		<pose>Unspecified</pose>
		<truncated>0</truncated>
		<difficult>0</difficult>
		<occluded>0</occluded>
		<bndbox>
			<xmin>414</xmin>
			<xmax>470</xmax>
			<ymin>535</ymin>
			<ymax>612</ymax>
		</bndbox>
	</object>
	<object>
		<name>rice</name>
		<pose>Unspecified</pose>
		<truncated>0</truncated>
		<difficult>0</difficult>
		<occluded>0</occluded>
		<bndbox>
			<xmin>363</xmin>
			<xmax>434</xmax>
			<ymin>547</ymin>
			<ymax>606</ymax>
		</bndbox>
	</object>
	<object>
		<name>rice</name>
		<pose>Unspecified</pose>
		<truncated>0</truncated>
		<difficult>0</difficult>
		<occluded>0</occluded>
		<bndbox>
			<xmin>403</xmin>
			<xmax>450</xmax>
			<ymin>471</ymin>
			<ymax>543</ymax>
		</bndbox>
	</object>
	<object>
		<name>rice</name>
		<pose>Unspecified</pose>
		<truncated>0</truncated>
		<difficult>0</difficult>
		<occluded>0</occluded>
		<bndbox>
			<xmin>422</xmin>
			<xmax>482</xmax>
			<ymin>435</ymin>
			<ymax>504</ymax>
		</bndbox>
	</object>
	<object>
		<name>rice</name>
		<pose>Unspecified</pose>
		<truncated>0</truncated>
		<difficult>0</difficult>
		<occluded>0</occluded>
		<bndbox>
			<xmin>448</xmin>
			<xmax>517</xmax>
			<ymin>422</ymin>
			<ymax>503</ymax>
		</bndbox>
	</object>
	<object>
		<name>rice</name>
		<pose>Unspecified</pose>
		<truncated>0</truncated>
		<difficult>0</difficult>
		<occluded>0</occluded>
		<bndbox>
			<xmin>469</xmin>
			<xmax>518</xmax>
			<ymin>361</ymin>
			<ymax>429</ymax>
		</bndbox>
	</object>
	<object>
		<name>rice</name>
		<pose>Unspecified</pose>
		<truncated>0</truncated>
		<difficult>0</difficult>
		<occluded>0</occluded>
		<bndbox>
			<xmin>339</xmin>
			<xmax>400</xmax>
			<ymin>403</ymin>
			<ymax>454</ymax>
		</bndbox>
	</object>
	<object>
		<name>rice</name>
		<pose>Unspecified</pose>
		<truncated>0</truncated>
		<difficult>0</difficult>
		<occluded>0</occluded>
		<bndbox>
			<xmin>114</xmin>
			<xmax>182</xmax>
			<ymin>434</ymin>
			<ymax>509</ymax>
		</bndbox>
	</object>
	<object>
		<name>rice</name>
		<pose>Unspecified</pose>
		<truncated>0</truncated>
		<difficult>0</difficult>
		<occluded>0</occluded>
		<bndbox>
			<xmin>136</xmin>
			<xmax>212</xmax>
			<ymin>422</ymin>
			<ymax>475</ymax>
		</bndbox>
	</object>
	<object>
		<name>rice</name>
		<pose>Unspecified</pose>
		<truncated>0</truncated>
		<difficult>0</difficult>
		<occluded>0</occluded>
		<bndbox>
			<xmin>172</xmin>
			<xmax>239</xmax>
			<ymin>440</ymin>
			<ymax>487</ymax>
		</bndbox>
	</object>
	<object>
		<name>rice</name>
		<pose>Unspecified</pose>
		<truncated>0</truncated>
		<difficult>0</difficult>
		<occluded>0</occluded>
		<bndbox>
			<xmin>221</xmin>
			<xmax>295</xmax>
			<ymin>442</ymin>
			<ymax>501</ymax>
		</bndbox>
	</object>
	<object>
		<name>rice</name>
		<pose>Unspecified</pose>
		<truncated>0</truncated>
		<difficult>0</difficult>
		<occluded>0</occluded>
		<bndbox>
			<xmin>258</xmin>
			<xmax>329</xmax>
			<ymin>407</ymin>
			<ymax>460</ymax>
		</bndbox>
	</object>
	<object>
		<name>rice</name>
		<pose>Unspecified</pose>
		<truncated>0</truncated>
		<difficult>0</difficult>
		<occluded>0</occluded>
		<bndbox>
			<xmin>293</xmin>
			<xmax>369</xmax>
			<ymin>374</ymin>
			<ymax>441</ymax>
		</bndbox>
	</object>
	<object>
		<name>rice</name>
		<pose>Unspecified</pose>
		<truncated>0</truncated>
		<difficult>0</difficult>
		<occluded>0</occluded>
		<bndbox>
			<xmin>223</xmin>
			<xmax>301</xmax>
			<ymin>394</ymin>
			<ymax>447</ymax>
		</bndbox>
	</object>
	<object>
		<name>rice</name>
		<pose>Unspecified</pose>
		<truncated>0</truncated>
		<difficult>0</difficult>
		<occluded>0</occluded>
		<bndbox>
			<xmin>190</xmin>
			<xmax>256</xmax>
			<ymin>368</ymin>
			<ymax>446</ymax>
		</bndbox>
	</object>
	<object>
		<name>rice</name>
		<pose>Unspecified</pose>
		<truncated>0</truncated>
		<difficult>0</difficult>
		<occluded>0</occluded>
		<bndbox>
			<xmin>227</xmin>
			<xmax>300</xmax>
			<ymin>345</ymin>
			<ymax>410</ymax>
		</bndbox>
	</object>
	<object>
		<name>rice</name>
		<pose>Unspecified</pose>
		<truncated>0</truncated>
		<difficult>0</difficult>
		<occluded>0</occluded>
		<bndbox>
			<xmin>263</xmin>
			<xmax>326</xmax>
			<ymin>305</ymin>
			<ymax>368</ymax>
		</bndbox>
	</object>
	<object>
		<name>rice</name>
		<pose>Unspecified</pose>
		<truncated>0</truncated>
		<difficult>0</difficult>
		<occluded>0</occluded>
		<bndbox>
			<xmin>290</xmin>
			<xmax>340</xmax>
			<ymin>323</ymin>
			<ymax>395</ymax>
		</bndbox>
	</object>
	<object>
		<name>rice</name>
		<pose>Unspecified</pose>
		<truncated>0</truncated>
		<difficult>0</difficult>
		<occluded>0</occluded>
		<bndbox>
			<xmin>320</xmin>
			<xmax>377</xmax>
			<ymin>343</ymin>
			<ymax>418</ymax>
		</bndbox>
	</object>
	<object>
		<name>rice</name>
		<pose>Unspecified</pose>
		<truncated>0</truncated>
		<difficult>0</difficult>
		<occluded>0</occluded>
		<bndbox>
			<xmin>322</xmin>
			<xmax>362</xmax>
			<ymin>306</ymin>
			<ymax>362</ymax>
		</bndbox>
	</object>
	<object>
		<name>rice</name>
		<pose>Unspecified</pose>
		<truncated>0</truncated>
		<difficult>0</difficult>
		<occluded>0</occluded>
		<bndbox>
			<xmin>351</xmin>
			<xmax>399</xmax>
			<ymin>335</ymin>
			<ymax>406</ymax>
		</bndbox>
	</object>
	<object>
		<name>rice</name>
		<pose>Unspecified</pose>
		<truncated>0</truncated>
		<difficult>0</difficult>
		<occluded>0</occluded>
		<bndbox>
			<xmin>387</xmin>
			<xmax>457</xmax>
			<ymin>382</ymin>
			<ymax>443</ymax>
		</bndbox>
	</object>
	<object>
		<name>rice</name>
		<pose>Unspecified</pose>
		<truncated>0</truncated>
		<difficult>0</difficult>
		<occluded>0</occluded>
		<bndbox>
			<xmin>393</xmin>
			<xmax>462</xmax>
			<ymin>362</ymin>
			<ymax>423</ymax>
		</bndbox>
	</object>
	<object>
		<name>rice</name>
		<pose>Unspecified</pose>
		<truncated>0</truncated>
		<difficult>0</difficult>
		<occluded>0</occluded>
		<bndbox>
			<xmin>444</xmin>
			<xmax>490</xmax>
			<ymin>347</ymin>
			<ymax>424</ymax>
		</bndbox>
	</object>
	<object>
		<name>rice</name>
		<pose>Unspecified</pose>
		<truncated>0</truncated>
		<difficult>0</difficult>
		<occluded>0</occluded>
		<bndbox>
			<xmin>427</xmin>
			<xmax>502</xmax>
			<ymin>306</ymin>
			<ymax>379</ymax>
		</bndbox>
	</object>
	<object>
		<name>rice</name>
		<pose>Unspecified</pose>
		<truncated>0</truncated>
		<difficult>0</difficult>
		<occluded>0</occluded>
		<bndbox>
			<xmin>435</xmin>
			<xmax>493</xmax>
			<ymin>259</ymin>
			<ymax>337</ymax>
		</bndbox>
	</object>
	<object>
		<name>rice</name>
		<pose>Unspecified</pose>
		<truncated>0</truncated>
		<difficult>0</difficult>
		<occluded>0</occluded>
		<bndbox>
			<xmin>382</xmin>
			<xmax>455</xmax>
			<ymin>289</ymin>
			<ymax>338</ymax>
		</bndbox>
	</object>
	<object>
		<name>rice</name>
		<pose>Unspecified</pose>
		<truncated>0</truncated>
		<difficult>0</difficult>
		<occluded>0</occluded>
		<bndbox>
			<xmin>362</xmin>
			<xmax>412</xmax>
			<ymin>308</ymin>
			<ymax>384</ymax>
		</bndbox>
	</object>
	<object>
		<name>rice</name>
		<pose>Unspecified</pose>
		<truncated>0</truncated>
		<difficult>0</difficult>
		<occluded>0</occluded>
		<bndbox>
			<xmin>335</xmin>
			<xmax>413</xmax>
			<ymin>266</ymin>
			<ymax>326</ymax>
		</bndbox>
	</object>
	<object>
		<name>rice</name>
		<pose>Unspecified</pose>
		<truncated>0</truncated>
		<difficult>0</difficult>
		<occluded>0</occluded>
		<bndbox>
			<xmin>338</xmin>
			<xmax>402</xmax>
			<ymin>227</ymin>
			<ymax>297</ymax>
		</bndbox>
	</object>
	<object>
		<name>rice</name>
		<pose>Unspecified</pose>
		<truncated>0</truncated>
		<difficult>0</difficult>
		<occluded>0</occluded>
		<bndbox>
			<xmin>363</xmin>
			<xmax>425</xmax>
			<ymin>211</ymin>
			<ymax>286</ymax>
		</bndbox>
	</object>
	<object>
		<name>rice</name>
		<pose>Unspecified</pose>
		<truncated>0</truncated>
		<difficult>0</difficult>
		<occluded>0</occluded>
		<bndbox>
			<xmin>397</xmin>
			<xmax>470</xmax>
			<ymin>249</ymin>
			<ymax>303</ymax>
		</bndbox>
	</object>
	<object>
		<name>rice</name>
		<pose>Unspecified</pose>
		<truncated>0</truncated>
		<difficult>0</difficult>
		<occluded>0</occluded>
		<bndbox>
			<xmin>398</xmin>
			<xmax>472</xmax>
			<ymin>210</ymin>
			<ymax>269</ymax>
		</bndbox>
	</object>
	<object>
		<name>rice</name>
		<pose>Unspecified</pose>
		<truncated>0</truncated>
		<difficult>0</difficult>
		<occluded>0</occluded>
		<bndbox>
			<xmin>365</xmin>
			<xmax>441</xmax>
			<ymin>159</ymin>
			<ymax>214</ymax>
		</bndbox>
	</object>
	<object>
		<name>rice</name>
		<pose>Unspecified</pose>
		<truncated>0</truncated>
		<difficult>0</difficult>
		<occluded>0</occluded>
		<bndbox>
			<xmin>387</xmin>
			<xmax>469</xmax>
			<ymin>182</ymin>
			<ymax>246</ymax>
		</bndbox>
	</object>
	<object>
		<name>rice</name>
		<pose>Unspecified</pose>
		<truncated>0</truncated>
		<difficult>0</difficult>
		<occluded>0</occluded>
		<bndbox>
			<xmin>433</xmin>
			<xmax>500</xmax>
			<ymin>158</ymin>
			<ymax>230</ymax>
		</bndbox>
	</object>
	<object>
		<name>rice</name>
		<pose>Unspecified</pose>
		<truncated>0</truncated>
		<difficult>0</difficult>
		<occluded>0</occluded>
		<bndbox>
			<xmin>156</xmin>
			<xmax>220</xmax>
			<ymin>186</ymin>
			<ymax>264</ymax>
		</bndbox>
	</object>
</annotation>
